Workbook

Sheet Sheet1
A1: invoice_id | B1: invoice_date | C1: invoice_pono | D1: invoice_podate | E1: customer_phone | F1: customer_name | G1: customer_gst | H1: customer_address | I1: customer_email | J1: customer_pincode | K1: vehicle_model | L1: vehicle_make | M1: vehicle_license_plate_no | N1: vehicle_external_bikeid | O1: vehicle_registration_no | P1: vehicle_year_of_manufacture | Q1: vehicle_fuel_type | R1: vehicle_transmission_type | S1: vehicle_engine_no | T1: vehicle_chassis_no | U1: vehicle_vin_no | V1: vehicle_color | W1: vehicle_reg_state | X1: vehicle_reg_exp
A2: F0116-C3678 | B2: =VLOOKUP(A2,Sheet2!$A$2:$R$3432,2,0) -> 2025-01-16 19:45:21 | C2: - | D2: - | E2: =VLOOKUP(A2,Sheet2!$A$2:$R$3432,4,0) -> 7887425646 | F2: =VLOOKUP(A2,Sheet2!$A$2:$R$3432,3,0) -> Avinash Jadhav | G2: - | H2: - | I2: - | J2: - | K2: =VLOOKUP(A2,Sheet2!$A$2:$R$3432,6,0) -> Yamaha Gladiator G5 | L2: - | M2: =VLOOKUP(A2,Sheet2!$A$2:$R$3432,5,0) -> MH28AD2026 | N2: - | O2: - | P2: - | Q2: - | R2: - | S2: =VLOOKUP(A2,Sheet2!$A$2:$R$3432,18,0) -> 35B404594 | T2: =VLOOKUP(A2,Sheet2!$A$2:$R$3432,17,0) -> ME1358044C2046624
A3: F0116-C3680 | B3: =VLOOKUP(A3,Sheet2!$A$2:$R$3432,2,0) -> 2025-01-16 19:56:55 | C3: - | D3: - | E3: =VLOOKUP(A3,Sheet2!$A$2:$R$3432,4,0) -> 9762184184 | F3: =VLOOKUP(A3,Sheet2!$A$2:$R$3432,3,0) -> AMOL CHITTE | G3: - | H3: - | I3: - | J3: - | K3: =VLOOKUP(A3,Sheet2!$A$2:$R$3432,6,0) -> Yamaha FZ 1 | L3: - | M3: =VLOOKUP(A3,Sheet2!$A$2:$R$3432,5,0) -> MH28AF8597 | N3: - | O3: - | P3: - | Q3: - | R3: - | S3: =VLOOKUP(A3,Sheet2!$A$2:$R$3432,18,0) | T3: =VLOOKUP(A3,Sheet2!$A$2:$R$3432,17,0)
A4: F0116-C3672 | B4: =VLOOKUP(A4,Sheet2!$A$2:$R$3432,2,0) -> 2025-01-16 19:53:58 | C4: - | D4: - | E4: =VLOOKUP(A4,Sheet2!$A$2:$R$3432,4,0) -> 9049536462 | F4: =VLOOKUP(A4,Sheet2!$A$2:$R$3432,3,0) -> MANOJ CHAUDHARI | G4: - | H4: - | I4: - | J4: - | K4: =VLOOKUP(A4,Sheet2!$A$2:$R$3432,6,0) -> Honda Activa 125 | L4: - | M4: =VLOOKUP(A4,Sheet2!$A$2:$R$3432,5,0) -> MH12TW0951 | N4: - | O4: - | P4: - | Q4: - | R4: - | S4: =VLOOKUP(A4,Sheet2!$A$2:$R$3432,18,0) -> JK13EG1004280 | T4: =VLOOKUP(A4,Sheet2!$A$2:$R$3432,17,0) -> ME4JK133LMG001221
A5: F0115-C3666 | B5: =VLOOKUP(A5,Sheet2!$A$2:$R$3432,2,0) -> 2025-01-16 19:58:37 | C5: - | D5: - | E5: =VLOOKUP(A5,Sheet2!$A$2:$R$3432,4,0) -> 9049536462 | F5: =VLOOKUP(A5,Sheet2!$A$2:$R$3432,3,0) -> Manoj | G5: - | H5: - | I5: - | J5: - | K5: =VLOOKUP(A5,Sheet2!$A$2:$R$3432,6,0) -> Honda Activa | L5: - | M5: =VLOOKUP(A5,Sheet2!$A$2:$R$3432,5,0) -> MH14ES3499 | N5: - | O5: - | P5: - | Q5: - | R5: - | S5: =VLOOKUP(A5,Sheet2!$A$2:$R$3432,18,0) | T5: =VLOOKUP(A5,Sheet2!$A$2:$R$3432,17,0) -> ME4JF502LE8313692
A6: F0113-C3659 | B6: =VLOOKUP(A6,Sheet2!$A$2:$R$3432,2,0) -> 2025-01-16 19:59:01 | C6: - | D6: - | E6: =VLOOKUP(A6,Sheet2!$A$2:$R$3432,4,0) -> 9049536462 | F6: =VLOOKUP(A6,Sheet2!$A$2:$R$3432,3,0) -> Manoj | G6: - | H6: - | I6: - | J6: - | K6: =VLOOKUP(A6,Sheet2!$A$2:$R$3432,6,0) -> Honda Activa | L6: - | M6: =VLOOKUP(A6,Sheet2!$A$2:$R$3432,5,0) -> MH14GB8855 | N6: - | O6: - | P6: - | Q6: - | R6: - | S6: =VLOOKUP(A6,Sheet2!$A$2:$R$3432,18,0) -> JF50U3017142 | T6: =VLOOKUP(A6,Sheet2!$A$2:$R$3432,17,0) -> ME4JF507BHU017099
A7: F0116-C3682 | B7: =VLOOKUP(A7,Sheet2!$A$2:$R$3432,2,0) -> 2025-01-16 20:36:29 | C7: - | D7: - | E7: =VLOOKUP(A7,Sheet2!$A$2:$R$3432,4,0) -> 9503093379 | F7: =VLOOKUP(A7,Sheet2!$A$2:$R$3432,3,0) -> VIPUL GUNJAL | G7: - | H7: - | I7: - | J7: - | K7: =VLOOKUP(A7,Sheet2!$A$2:$R$3432,6,0) -> TVS Scooty PEP | L7: - | M7: =VLOOKUP(A7,Sheet2!$A$2:$R$3432,5,0) -> MH14BV6616 | N7: - | O7: - | P7: - | Q7: - | R7: - | S7: =VLOOKUP(A7,Sheet2!$A$2:$R$3432,18,0) | T7: =VLOOKUP(A7,Sheet2!$A$2:$R$3432,17,0)
A8: F0116-C3675 | B8: =VLOOKUP(A8,Sheet2!$A$2:$R$3432,2,0) -> 2025-01-16 20:37:46 | C8: - | D8: - | E8: =VLOOKUP(A8,Sheet2!$A$2:$R$3432,4,0) -> 9146437954 | F8: =VLOOKUP(A8,Sheet2!$A$2:$R$3432,3,0) -> Archana Shingare | G8: - | H8: - | I8: - | J8: - | K8: =VLOOKUP(A8,Sheet2!$A$2:$R$3432,6,0) -> TVS Scooty PEP Plus | L8: - | M8: =VLOOKUP(A8,Sheet2!$A$2:$R$3432,5,0) -> MH14GV7627 | N8: - | O8: - | P8: - | Q8: - | R8: - | S8: =VLOOKUP(A8,Sheet2!$A$2:$R$3432,18,0) -> AG3AJ2937060 | T8: =VLOOKUP(A8,Sheet2!$A$2:$R$3432,17,0) -> MD626FG38J2AG0938
A9: F0116-C3676 | B9: =VLOOKUP(A9,Sheet2!$A$2:$R$3432,2,0) -> 2025-01-16 20:37:08 | C9: - | D9: - | E9: =VLOOKUP(A9,Sheet2!$A$2:$R$3432,4,0) -> 7385942438 | F9: =VLOOKUP(A9,Sheet2!$A$2:$R$3432,3,0) -> Anchal | G9: - | H9: - | I9: - | J9: - | K9: =VLOOKUP(A9,Sheet2!$A$2:$R$3432,6,0) -> Honda Activa 110 | L9: - | M9: =VLOOKUP(A9,Sheet2!$A$2:$R$3432,5,0) -> MH27AZ5188 | N9: - | O9: - | P9: - | Q9: - | R9: - | S9: =VLOOKUP(A9,Sheet2!$A$2:$R$3432,18,0) -> JF50E82558366 | T9: =VLOOKUP(A9,Sheet2!$A$2:$R$3432,17,0) -> ME4JF301KD8559676
A10: F0116-C3673 | B10: =VLOOKUP(A10,Sheet2!$A$2:$R$3432,2,0) -> 2025-01-16 20:38:01 | C10: - | D10: - | E10: =VLOOKUP(A10,Sheet2!$A$2:$R$3432,4,0) -> 9673758691 | F10: =VLOOKUP(A10,Sheet2!$A$2:$R$3432,3,0) -> RUSHIKESH SHELKE | G10: - | H10: - | I10: - | J10: - | K10: =VLOOKUP(A10,Sheet2!$A$2:$R$3432,6,0) -> Yamaha FZ No Data | L10: - | M10: =VLOOKUP(A10,Sheet2!$A$2:$R$3432,5,0) -> MH12RB1925 | N10: - | O10: - | P10: - | Q10: - | R10: - | S10: =VLOOKUP(A10,Sheet2!$A$2:$R$3432,18,0) -> G3H7E0071904 | T10: =VLOOKUP(A10,Sheet2!$A$2:$R$3432,17,0) -> ME1G4219J0046776
A11: F0116-C3674 | B11: =VLOOKUP(A11,Sheet2!$A$2:$R$3432,2,0) -> 2025-01-16 19:58:04 | C11: - | D11: - | E11: =VLOOKUP(A11,Sheet2!$A$2:$R$3432,4,0) -> 8999016024 | F11: =VLOOKUP(A11,Sheet2!$A$2:$R$3432,3,0) -> TUSHAR RAUT | G11: - | H11: - | I11: - | J11: - | K11: =VLOOKUP(A11,Sheet2!$A$2:$R$3432,6,0) -> Yamaha FZ 25 | L11: - | M11: =VLOOKUP(A11,Sheet2!$A$2:$R$3432,5,0) -> MH16CW6540 | N11: - | O11: - | P11: - | Q11: - | R11: - | S11: =VLOOKUP(A11,Sheet2!$A$2:$R$3432,18,0) -> G3P1E0009245 | T11: =VLOOKUP(A11,Sheet2!$A$2:$R$3432,17,0) -> ME1RG6916M00005498
A12: F0116-C3679 | B12: =VLOOKUP(A12,Sheet2!$A$2:$R$3432,2,0) -> 2025-01-16 19:55:46 | C12: - | D12: - | E12: =VLOOKUP(A12,Sheet2!$A$2:$R$3432,4,0) -> 8237987263 | F12: =VLOOKUP(A12,Sheet2!$A$2:$R$3432,3,0) -> Jaideep | G12: - | H12: - | I12: - | J12: - | K12: =VLOOKUP(A12,Sheet2!$A$2:$R$3432,6,0) -> Hero Deluxe HF | L12: - | M12: =VLOOKUP(A12,Sheet2!$A$2:$R$3432,5,0) -> MH16CB4601 | N12: - | O12: - | P12: - | Q12: - | R12: - | S12: =VLOOKUP(A12,Sheet2!$A$2:$R$3432,18,0) | T12: =VLOOKUP(A12,Sheet2!$A$2:$R$3432,17,0)
A13: F0116-C3681 | B13: =VLOOKUP(A13,Sheet2!$A$2:$R$3432,2,0) -> 2025-01-16 19:43:47 | C13: - | D13: - | E13: =VLOOKUP(A13,Sheet2!$A$2:$R$3432,4,0) -> 9930836131 | F13: =VLOOKUP(A13,Sheet2!$A$2:$R$3432,3,0) -> Mithesh shroff | G13: - | H13: - | I13: - | J13: - | K13: =VLOOKUP(A13,Sheet2!$A$2:$R$3432,6,0) -> Suzuki Access 125 | L13: - | M13: =VLOOKUP(A13,Sheet2!$A$2:$R$3432,5,0) -> MH12HM6830 | N13: - | O13: - | P13: - | Q13: - | R13: - | S13: =VLOOKUP(A13,Sheet2!$A$2:$R$3432,18,0) | T13: =VLOOKUP(A13,Sheet2!$A$2:$R$3432,17,0)
... A3432: F0726-C5471 | B3432: =VLOOKUP(A3432,Sheet2!$A$2:$R$3432,2,0) -> 2025-07-26 20:31:42 | C3432: - | D3432: - | E3432: =VLOOKUP(A3432,Sheet2!$A$2:$R$3432,4,0) -> 9766589338 | F3432: =VLOOKUP(A3432,Sheet2!$A$2:$R$3432,3,0) -> Prathamesh Nikam | G3432: - | H3432: - | I3432: - | J3432: - | K3432: =VLOOKUP(A3432,Sheet2!$A$2:$R$3432,6,0) -> TVS Jupiter | L3432: - | M3432: =VLOOKUP(A3432,Sheet2!$A$2:$R$3432,5,0) -> MH12NH1362 | N3432: - | O3432: - | P3432: - | Q3432: - | R3432: - | S3432: =VLOOKUP(A3432,Sheet2!$A$2:$R$3432,18,0) | T3432: =VLOOKUP(A3432,Sheet2!$A$2:$R$3432,17,0)

Sheet Sheet2
A1: Jobcard Number | B1: Date | C1: Customer Name | D1: Mobile Number | E1: Vehicle Number | F1: Vehicle Details | G1: KM | H1: Discount | I1: Balance | J1: Received | K1: Total | L1: Final | M1: Spare Total | N1: Lube Total | O1: Job Total | P1: Payment Method | Q1: Chassis Number | R1: Engine Number
A2: F0116-C3678 | B2: 2025-01-16 19:45:21 | C2: Avinash Jadhav | D2: 7887425646 | E2: MH28AD2026 | F2: Yamaha Gladiator G5 | G2: 06043 | H2: 0 ₹ | I2: 0 | J2: 2863 | K2: 2863 | L2: 2863 | M2: 1580 | N2: 659 | O2: 624 | P2: UPI | Q2: ME1358044C2046624 | R2: 35B404594
A3: F0116-C3672 | B3: 2025-01-16 19:53:58 | C3: MANOJ CHAUDHARI | D3: 9049536462 | E3: MH12TW0951 | F3: Honda Activa 125 | G3: 27296 | H3: 0 ₹ | I3: 0 | J3: 1534 | K3: 1534 | L3: 1534 | M3: 355 | N3: 730 | O3: 449 | P3: UPI | Q3: ME4JK133LMG001221 | R3: JK13EG1004280
A4: F0116-C3680 | B4: 2025-01-16 19:56:55 | C4: AMOL CHITTE | D4: 9762184184 | E4: MH28AF8597 | F4: Yamaha FZ 1 | G4: 01 | H4: 0 ₹ | I4: 0 | J4: 1600 | K4: 1600 | L4: 1600 | M4: 1600 | N4: 0 | O4: 0 | P4: UPI
A5: F0113-C3659 | B5: 2025-01-16 19:59:01 | C5: Manoj | D5: 9049536462 | E5: MH14GB8855 | F5: Honda Activa | G5: 10344 | H5: 0 ₹ | I5: 0 | J5: 2887 | K5: 2887 | L5: 2887 | M5: 1633 | N5: 730 | O5: 524 | P5: UPI | Q5: ME4JF507BHU017099 | R5: JF50U3017142
A6: F0115-C3666 | B6: 2025-01-16 19:58:37 | C6: Manoj | D6: 9049536462 | E6: MH14ES3499 | F6: Honda Activa | G6: 54202 | H6: 0 ₹ | I6: 0 | J6: 1614 | K6: 1614 | L6: 1614 | M6: 360 | N6: 730 | O6: 524 | P6: UPI | Q6: ME4JF502LE8313692
A7: F0116-C3675 | B7: 2025-01-16 20:37:46 | C7: Archana Shingare | D7: 9146437954 | E7: MH14GV7627 | F7: TVS Scooty PEP Plus | G7: 29803 | H7: 064 ₹ | I7: 0 | J7: 1300 | K7: 1364 | L7: 1300 | M7: 185 | N7: 730 | O7: 449 | P7: UPI | Q7: MD626FG38J2AG0938 | R7: AG3AJ2937060
A8: F0116-C3682 | B8: 2025-01-16 20:36:29 | C8: VIPUL GUNJAL | D8: 9503093379 | E8: MH14BV6616 | F8: TVS Scooty PEP | G8: 19290 | H8: 0 ₹ | I8: 0 | J8: 4831 | K8: 4831 | L8: 4831 | M8: 901 | N8: 460 | O8: 3470 | P8: Cash
A9: E1129-C3202 | B9: 2024-11-30 10:40:50 | C9: Aditya Gupta | D9: 9881100507 | E9: MH14CV3016 | F9: Honda Activa 110 | G9: 12432 | H9: 0 ₹ | I9: 0 | J9: 1861 | K9: 1861 | L9: 1861 | M9: 618 | N9: 719 | O9: 524 | P9: UPI | Q9: ME4JC448EE823812 | R9: JC44E1349771
A10: E1127-C3183 | B10: 2024-11-30 10:48:50 | C10: Pratik | D10: 7410515046 | E10: MH12TG8914 | F10: KTM Duke 200 | G10: 9145 | H10: 0 ₹ | I10: 0 | J10: 1856 | K10: 1856 | L10: 1856 | M10: 1029 | N10: 128 | O10: 699 | P10: UPI
A11: E1129-C3199 | B11: 2024-11-30 10:39:26 | C11: Gaurang | D11: 9657702581 | E11: MH14CR5954 | F11: Bajaj Discover No Data | G11: 62363 | H11: 0 ₹ | I11: 0 | J11: 1643 | K11: 1643 | L11: 1643 | M11: 410 | N11: 784 | O11: 449 | P11: Cash | Q11: MDZDSJZZZTWK58252 | R11: MZMBTJ66869
A12: E1129-C3201 | B12: 2024-11-30 10:46:56 | C12: Suhas | D12: 8483833982 | E12: MH17BE1314 | F12: Honda Dio | G12: 41479 | H12: 0 ₹ | I12: 0 | J12: 1743 | K12: 1743 | L12: 1743 | M12: 420 | N12: 719 | O12: 604 | P12: Card | Q12: MEGJF392JE211927 | R12: JF39E70211907
A13: E1129-C3200 | B13: 2024-11-30 10:43:27 | C13: Himanshu Chothe | D13: 8237320223 | E13: MH12TW3707 | F13: Honda Activa 6G | G13: 13562 | H13: 0 ₹ | I13: 0 | J13: 1214 | K13: 1214 | L13: 1214 | M13: 120 | N13: 645 | O13: 449 | P13: UPI | Q13: ME4JF918LMG087052 | R13: JF91EG508758
A14: E1129-C3203 | B14: 2024-11-30 10:44:32 | C14: Rahil Shaikh | D14: 7507365078 | E14: MH15JE1843 | F14: Hero Xpulse 200 | G14: 21362 | H14: 0 ₹ | I14: 0 | J14: 629 | K14: 629 | L14: 629 | M14: 80 | N14: 0 | O14: 549 | P14: UPI | Q14: MC20AHMGKB1000 | R14: MBLDL061NGK2237
A15: E1220-C3415 | B15: 2024-12-20 20:33:38 | C15: Paresh Patil | D15: 7218664927 | E15: MH12KR6021 | F15: Hero Passion Pro | G15: 9577 | H15: 0 ₹ | I15: 0 | J15: 1511 | K15: 1511 | L15: 1511 | M15: 572 | N15: 190 | O15: 749 | P15: UPI
A16: E1129-C3196 | B16: 2024-11-30 10:51:51 | C16: Saurabh Nagarkar | D16: 9657081177 | E16: MH14HN0727 | F16: Bajaj Pulsar 220F | G16: 46530 | H16: 0 ₹ | I16: 0 | J16: 2309 | K16: 2309 | L16: 2309 | M16: 473 | N16: 962 | O16: 874 | P16: UPI | Q16: MD2A13EY3KLC10429 | R16: DK4CK1L01168
A17: E1129-C3205 | B17: 2024-11-30 10:38:13 | C17: Raj | D17: 8982156364 | E17: MH12TP0950 | F17: TVS Apache 160 4V | G17: 23304 | H17: 0 ₹ | I17: 0 | J17: 840 | K17: 840 | L17: 840 | M17: 391 | N17: 0 | O17: 449 | P17: Cash | Q17: MD637DE50M2D01233 | R17: GE5DM2X01136
A18: E1129-C3197 | B18: 2024-11-30 10:47:56 | C18: Renuka Patel | D18: 8888520035 | E18: MH27DC6939 | F18: Honda Activa 6G | G18: 6294 | H18: 0 ₹ | I18: 0 | J18: 1349 | K18: 1349 | L18: 1349 | M18: 255 | N18: 645 | O18: 449 | P18: UPI | Q18: ME4JF918KMW053320 | R18: JF91EW5053371
A19: E1127-C3185 | B19: 2024-11-30 10:55:00 | C19: Kumar | D19: 9673530315 | E19: MH12MJ9674 | F19: Honda Activa 3G | G19: 28651 | H19: 0 ₹ | I19: 0 | J19: 1591 | K19: 1591 | L19: 1591 | M19: 410 | N19: 657 | O19: 524 | P19: UPI
A20: E1127-C3182 | B20: 2024-11-30 10:56:48 | C20: Akshay | D20: 8484088353 | E20: MH14GK4333 | F20: Honda Activa 4G | G20: 40639 | H20: 0 ₹ | I20: 0 | J20: 2045 | K20: 2045 | L20: 2045 | M20: 791 | N20: 730 | O20: 524 | P20: UPI | Q20: ME4JF507GHU424715 | R20: JF50EU5424616
A21: E1129-C3198 | B21: 2024-11-30 10:47:20 | C21: Sujay Joshi | D21: 9890675383 | E21: MH12QQ8618 | F21: Suzuki Access 125 | G21: 2358 | H21: 0 ₹ | I21: 0 | J21: 1200 | K21: 1200 | L21: 1200 | M21: 1150 | N21: 0 | O21: 50 | P21: UPI | Q21: MB8DP11AFJ8925232 | R21: AF211722746
A22: E1128-C3190 | B22: 2024-11-30 11:27:00 | C22: Somesh More | D22: 7588710115 | E22: MH17BF7914 | F22: TVS Jupiter | G22: 26917 | H22: 0 ₹ | I22: 0 | J22: 1960 | K22: 1960 | L22: 1960 | M22: 781 | N22: 730 | O22: 449 | P22: UPI | Q22: MD626BG41E1N65539 | R22: BG4NE1359276
A23: E1128-C3195 | B23: 2024-11-30 10:58:28 | C23: SHAILESH KHANDAGALE | D23: 7840978199 | E23: MH45AG5687 | F23: Honda Shine | G23: 38384 | H23: 0 ₹ | I23: 0 | J23: 1589 | K23: 1589 | L23: 1589 | M23: 356 | N23: 784 | O23: 449 | P23: UPI | Q23: ME4JC654EH7087173 | R23: JC65E71127864
A24: E1127-C3187 | B24: 2024-11-30 10:52:58 | C24: KISHOR CHAURE | D24: 9767809683 | E24: MH14GF9795 | F24: Honda Activa 4G | G24: 33544 | H24: 0 ₹ | I24: 0 | J24: 1564 | K24: 1564 | L24: 1564 | M24: 310 | N24: 730 | O24: 524 | P24: UPI | Q24: ME4JF5070H4123771 | R24: JF50E451239332
A25: E1128-C3192 | B25: 2024-11-30 11:28:09 | C25: CHINMAY | D25: 8237668546 | E25: MH20FF0016 | F25: Bajaj Pulsar 200 RS | G25: 37680 | H25: 0 ₹ | I25: 0 | J25: 1926 | K25: 1926 | L25: 1926 | M25: 1301 | N25: 0 | O25: 625 | P25: UPI | R25: JLYCK246904
A26: E1128-C3191 | B26: 2024-11-30 11:23:05 | C26: Atul Kad | D26: 8149471510 | E26: MH21BJ2493 | F26: Suzuki Intruder 150 | G26: 25910 | H26: 0 ₹ | I26: 0 | J26: 1671 | K26: 1671 | L26: 1671 | M26: 288 | N26: 784 | O26: 599 | P26: UPI | Q26: 8105090 | R26: 473507
A27: E1128-C3193 | B27: 2024-11-30 11:31:02 | C27: Girish Kinikar | D27: 9579717727 | E27: MH19CD1462 | F27: Honda Activa 3G | G27: 10999 | H27: 0 ₹ | I27: 0 | J27: 1454 | K27: 1454 | L27: 1454 | M27: 200 | N27: 730 | O27: 524 | P27: Cash | Q27: ME4JF504EFT349427 | R27: JF50ET2350274
A28: E1128-C3189 | B28: 2024-11-30 11:29:32 | C28: Sunny | D28: 9607926002 | E28: MH12HU5357 | F28: TVS Scooty PEP Plus | G28: 28773 | H28: 0 ₹ | I28: 0 | J28: 1609 | K28: 1609 | L28: 1609 | M28: 430 | N28: 730 | O28: 449 | P28: UPI | Q28: MD626BG39B2N18935 | R28: 2633859
A29: E1106-C2987 | B29: 2024-11-30 11:32:56 | C29: ADITYA SINHG | D29: 9172523743 | E29: MH11AA9796 | F29: Bajaj Pulsar 150 | G29: 23359 | H29: 0 ₹ | I29: 0 | J29: 2303 | K29: 2303 | L29: 2303 | M29: 2028 | N29: 0 | O29: 275 | P29: UPI
A30: E1130-C3208 | B30: 2024-11-30 20:17:57 | C30: Rohit | D30: 7620002519 | E30: MH22AY9183 | F30: Honda Shine SP | G30: 19716 | H30: 0 ₹ | I30: 0 | J30: 1399 | K30: 1399 | L30: 1399 | M30: 166 | N30: 784 | O30: 449 | P30: UPI | Q30: ME4JC83EHNG077818 | R30: JC83EG3234540
A31: E1220-C3410 | B31: 2024-12-20 20:36:30 | C31: Santosh Bhalerao | D31: 8275204492 | E31: MH12BU7746 | F31: Hero Splendor | G31: 11804 | H31: 0 ₹ | I31: 0 | J31: 4552 | K31: 4552 | L31: 4552 | M31: 3188 | N31: 190 | O31: 1174 | P31: UPI
A32: E1130-C3210 | B32: 2024-11-30 20:07:02 | C32: RAM NARESH | D32: 9175645184 | E32: MH12QP5582 | F32: TVS Victor | G32: 109897 | H32: 0 ₹ | I32: 0 | J32: 1374 | K32: 1374 | L32: 1374 | M32: 435 | N32: 190 | O32: 749 | P32: UPI | Q32: MD625GF11J1E23809 | R32: LE1EJ1714914
A33: E1220-C3411 | B33: 2024-12-20 20:32:13 | C33: Amit Salve | D33: 8261925966 | E33: MH12LS2093 | F33: Yamaha FZ | G33: 01 | H33: 0 ₹ | I33: 0 | J33: 7261 | K33: 7261 | L33: 7261 | M33: 4897 | N33: 900 | O33: 1464 | P33: UPI
A34: F0213-C3953 | B34: 2025-02-13 18:48:41 | C34: RAHUL GAIKWAD | D34: 9923763880 | E34: MH10BD1460 | F34: Honda Shine CB | G34: 33269 | H34: 0 ₹ | I34: 0 | J34: 3033 | K34: 3033 | L34: 3033 | M34: 1675 | N34: 784 | O34: 574 | P34: UPI
A35: E1130-C3218 | B35: 2024-11-30 20:15:51 | C35: LAXMIKANT | D35: 8668610879 | E35: MH16BS1559 | F35: Honda Activa 3G | G35: 43737 | H35: 0 ₹ | I35: 0 | J35: 695 | K35: 695 | L35: 695 | M35: 650 | N35: 0 | O35: 45 | P35: UPI | Q35: ME4JF50544TG430642 | R35: JF50ET3630768
A36: E1220-C3413 | B36: 2024-12-20 20:35:18 | C36: Dheeraj | D36: 7030469122 | E36: MH04KZ2927 | F36: Suzuki Gixxer SF | G36: 29937 | H36: 0 ₹ | I36: 0 | J36: 1708 | K36: 1708 | L36: 1708 | M36: 325 | N36: 784 | O36: 599 | P36: UPI
A37: E1220-C3416 | B37: 2024-12-20 17:12:04 | C37: Omkar Shirke | D37: 9923220239 | E37: MH12KD2649 | F37: TVS Wego Basic | G37: 39999 | H37: 0 ₹ | I37: 0 | J37: 2166 | K37: 2166 | L37: 2166 | M37: 2166 | N37: 0 | O37: 0 | P37: UPI | Q37: MD626AG46D1643177
A38: E1220-C3407 | B38: 2024-12-20 20:34:01 | C38: Rupesh | D38: 9762574209 | E38: MH20GR0562 | F38: Honda Activa 6G | G38: 5831 | H38: 0 ₹ | I38: 0 | J38: 1174 | K38: 1174 | L38: 1174 | M38: 80 | N38: 645 | O38: 449 | P38: UPI
A39: E1130-C3211 | B39: 2024-11-30 19:57:50 | C39: Venkatesh Kulkarni | D39: 9168712211 | E39: MH12JJ6470 | F39: Bajaj Avenger 220 Street | G39: 04974 | H39: 0 ₹ | I39: 0 | J39: 2198 | K39: 2198 | L39: 2198 | M39: 701 | N39: 898 | O39: 599 | P39: UPI | Q39: MDZAZEZOCCG12121 | R39: PDZCC0115556
A40: E1220-C3408 | B40: 2024-12-20 20:34:31 | C40: SANKALP YERAWAR | D40: 8237669414 | E40: MH14HP1653 | F40: Yamaha MT 15 | G40: 20305 | H40: 0 ₹ | I40: 0 | J40: 3233 | K40: 3233 | L40: 3233 | M40: 1525 | N40: 784 | O40: 924 | P40: UPI | Q40: ME1RG5913K0003326 | R40: G3K5E0086860
A41: E1129-C3204 | B41: 2024-11-30 20:09:49 | C41: Rasika | D41: 8010075578 | E41: MH14BW3591 | F41: Hero Pleasure | G41: 13002 | H41: 0 ₹ | I41: 0 | J41: 1587 | K41: 1587 | L41: 1587 | M41: 333 | N41: 730 | O41: 524 | P41: UPI | Q41: MBLJF16EC9G02273 | R41: JF16EA9GJ02158
A42: E1130-C3216 | B42: 2024-11-30 20:01:58 | C42: Meghraj Pawar | D42: 7841889046 | E42: MH13BW0594 | F42: Honda Trigger No Data | G42: 72734 | H42: 0 ₹ | I42: 0 | J42: 2063 | K42: 2063 | L42: 2063 | M42: 830 | N42: 784 | O42: 449 | P42: UPI | Q42: ME4KC191GE8047056 | R42: KC19E8006880
A43: E1220-C3417 | B43: 2024-12-20 20:35:40 | C43: Rakesh Kumar | D43: 9881240162 | E43: MH14HJ1530 | F43: TVS Jupiter | G43: 27112 | H43: 0 ₹ | I43: 0 | J43: 1259 | K43: 1259 | L43: 1259 | M43: 80 | N43: 730 | O43: 449 | P43: UPI | Q43: MD626EG42J1P121212 | R43: OG4PJ1604795
A44: E1130-C3220 | B44: 2024-11-30 20:14:41 | C44: VIKAS | D44: 8928284484 | E44: MH29AF3133 | F44: Suzuki Access 125 | G44: 30063 | H44: 0 ₹ | I44: 0 | J44: 2574 | K44: 2574 | L44: 2574 | M44: 2574 | N44: 0 | O44: 0 | P44: Cash | Q44: MB8CF4KCB240273 | R44: CF4862235936
A45: E1130-C3214 | B45: 2024-11-30 20:03:35 | C45: Rajiv | D45: 9833086094 | E45: MH14DC1513 | F45: Honda Activa 110 | G45: 46000 | H45: 0 ₹ | I45: 0 | J45: 1924 | K45: 1924 | L45: 1924 | M45: 670 | N45: 730 | O45: 524 | P45: UPI | Q45: ME4JC448JB8497741 | R45: JC44E1608711
A46: E1130-C3217 | B46: 2024-11-30 20:15:00 | C46: Lahane | D46: 9822398525 | E46: MH14EL2835 | F46: TVS Wego No Data | G46: 01 | H46: 0 ₹ | I46: 0 | J46: 5990 | K46: 5990 | L46: 5990 | M46: 5075 | N46: 540 | O46: 375 | P46: Cash
A47: E1130-C3207 | B47: 2024-11-30 20:16:28 | C47: Sagar Dhamale | D47: 9552810707 | E47: MH20CX6684 | F47: Royal Enfield Classic 350 | G47: 42903 | H47: 0 ₹ | I47: 0 | J47: 8815 | K47: 8815 | L47: 8815 | M47: 5764 | N47: 1552 | O47: 1499 | P47: UPI | Q47: MD637DESOMZD01233 | R47: GESDMZX01136
A48: E1130-C3215 | B48: 2024-11-30 20:16:50 | C48: Ganesh Khaire | D48: 8788252113 | E48: MH14JQ8996 | F48: TVS Jupiter | G48: 33913 | H48: 0 ₹ | I48: 0 | J48: 1227 | K48: 1227 | L48: 1227 | M48: 952 | N48: 0 | O48: 275 | P48: UPI
A49: E1130-C3212 | B49: 2024-11-30 20:08:16 | C49: SAMPATH KALOKHE | D49: 9890825583 | E49: MH14HT8660 | F49: Honda Unicorn 150 | G49: 22652 | H49: 0 ₹ | I49: 0 | J49: 2107 | K49: 2107 | L49: 2107 | M49: 518 | N49: 1140 | O49: 449 | P49: UPI | Q49: ME4KC315GKA103740 | R49: KC31EA1103668
A50: F0512-C4725 | B50: 2025-05-12 19:11:02 | C50: Kishor Tarange | D50: 8668946340 | E50: MH25AU7335 | F50: Hero Destini 125 | G50: 9662 | H50: 0 ₹ | I50: 0 | J50: 2130 | K50: 2130 | L50: 2130 | M50: 2130 | N50: 0 | O50: 0 | P50: Card
A51: E1130-C3219 | B51: 2024-11-30 20:44:54 | C51: Saurabh Khandekar | D51: 7028014990 | E51: MH10DW4975 | F51: Hero Destini 125 | G51: 6252 | H51: 0 ₹ | I51: 0 | J51: 1259 | K51: 1259 | L51: 1259 | M51: 80 | N51: 730 | O51: 449 | P51: UPI | Q51: MBLJFWZ49NGD02569 | R51: JF17EANGD03778
A52: F0510-C4699 | B52: 2025-05-12 19:12:33 | C52: Girish Satav | D52: 8793072076 | E52: MH12KG0010 | F52: Royal Enfield Classic 350 | G52: 19824 | H52: 0 ₹ | I52: 0 | J52: 6329 | K52: 6329 | L52: 6329 | M52: 3612 | N52: 1468 | O52: 1249 | P52: UPI
A53: E1130-C3213 | B53: 2024-11-30 20:19:06 | C53: Gajanan Mudlyar | D53: 9823123051 | E53: MH12MX8141 | F53: Honda Activa 3G | G53: 17718 | H53: 0 ₹ | I53: 0 | J53: 1634 | K53: 1634 | L53: 1634 | M53: 380 | N53: 730 | O53: 524 | P53: UPI | Q53: ME4JF505CGU028175 | R53: JF50EU3028152
A54: E1130-C3206 | B54: 2024-12-01 13:28:59 | C54: Shobhit Nitnare | D54: 7744067593 | E54: MH14FF711 | F54: Yamaha R15 | G54: 88580 | H54: 0 ₹ | I54: 0 | J54: 3616 | K54: 3616 | L54: 3616 | M54: 2133 | N54: 784 | O54: 699 | P54: Cash | Q54: ME1RG0629F0009000 | R54: G3E7E0047322
A55: E1130-C3221 | B55: 2024-12-01 13:32:58 | C55: Das Gupta | D55: 9545278631 | E55: MH12MH9808 | F55: Hero Pleasure | G55: 16942 | H55: 0 ₹ | I55: 0 | J55: 964 | K55: 964 | L55: 964 | M55: 280 | N55: 80 | O55: 604 | P55: UPI | Q55: MBLJF16EMFGJ045544 | R55: JF16EEFGJ05501
A56: F0213-C3952 | B56: 2025-02-13 19:45:08 | C56: SUBODH | D56: 9479244339 | E56: CG12AP6416 | F56: Hero Splendor Plus | G56: 24731 | H56: 0 ₹ | I56: 0 | J56: 2934 | K56: 2934 | L56: 2934 | M56: 1445 | N56: 190 | O56: 1299 | P56: UPI | R56: HA10ERG042352
A57: E1201-C3223 | B57: 2024-12-01 21:02:11 | C57: Saurabh Shinde | D57: 9595777496 | E57: MH34CC3562 | F57: Royal Enfield Bullet 350 | G57: 16760 | H57: 0 ₹ | I57: 0 | J57: 879 | K57: 879 | L57: 879 | M57: 80 | N57: 0 | O57: 799 | P57: UPI | Q57: ME3J3D5FKNT100345
A58: E1201-C3226 | B58: 2024-12-01 16:57:28 | C58: Vikrant Chavan | D58: 9359277762 | E58: MH14HH3024 | F58: Honda Activa 5G | G58: 28027 | H58: 0 ₹ | I58: 0 | J58: 1449 | K58: 1449 | L58: 1449 | M58: 160 | N58: 730 | O58: 559 | P58: UPI | Q58: ME4JF50BLJT297844 | R58: JF50ET8297249
A59: E1201-C3238 | B59: 2024-12-02 17:02:10 | C59: Deepak Raut | D59: 9960409602 | E59: MH14DU8185 | F59: Honda Shine HET | G59: 50000 | H59: 0 ₹ | I59: 0 | J59: 3700 | K59: 3700 | L59: 3700 | M59: 3700 | N59: 0 | O59: 0 | P59: UPI | Q59: ME4JC36KAD7154478
A60: E1201-C3222 | B60: 2024-12-01 16:53:00 | C60: Jayesh Mankar | D60: 8180900804 | E60: MH30AP8694 | F60: Honda Shine | G60: 46468 | H60: 0 ₹ | I60: 0 | J60: 1313 | K60: 1313 | L60: 1313 | M60: 80 | N60: 784 | O60: 449 | P60: UPI | Q60: M1E4JC36NBF7273634 | R60: JC36ET3958382
A61: E1201-C3225 | B61: 2024-12-01 21:01:27 | C61: Vartika Singh | D61: 8826459210 | E61: MH12SG8399 | F61: Honda Activa 5G | G61: 18187 | H61: 0 ₹ | I61: 0 | J61: 1567 | K61: 1567 | L61: 1567 | M61: 313 | N61: 730 | O61: 524 | P61: UPI | Q61: ME4JF50BGKW058661 | R61: JF50EW1058684
A62: F0117-C3683 | B62: 2025-01-17 20:53:13 | C62: Hitesh | D62: 9987725138 | E62: MH04LN6222 | F62: Yamaha FZ 25 | G62: 19267 | H62: 0 ₹ | I62: 0 | J62: 1751 | K62: 1751 | L62: 1751 | M62: 80 | N62: 972 | O62: 699 | P62: Card | Q62: ME1RG695BN0003691 | R62: G3P1E0018855
A63: E1201-C3224 | B63: 2024-12-01 18:56:24 | C63: Swaroop Kadam | D63: 8055607474 | E63: MH14GX4135 | F63: Honda Aviator | G63: 28462 | H63: 0 ₹ | I63: 0 | J63: 1592 | K63: 1592 | L63: 1592 | M63: 413 | N63: 730 | O63: 449 | P63: Card | Q63: ME4JF21DDJ8076385 | R63: JF21E82139979
A64: F0117-C3685 | B64: 2025-01-17 20:52:58 | C64: Ram Prasad | D64: 9158682999 | E64: MH12QV4996 | F64: Honda Activa 125 | G64: 01 | H64: 0 ₹ | I64: 0 | J64: 1344 | K64: 1344 | L64: 1344 | M64: 165 | N64: 730 | O64: 449 | P64: UPI
A65: F0117-C3684 | B65: 2025-01-17 20:54:19 | C65: Vaibhav Pathak | D65: 9922986199 | E65: MH14HB1856 | F65: Honda Activa i | G65: 20933 | H65: 0 ₹ | I65: 0 | J65: 1499 | K65: 1499 | L65: 1499 | M65: 245 | N65: 730 | O65: 524 | P65: UPI | Q65: ME4JF48CGJ8002907
A66: F0115-C3669 | B66: 2025-01-17 20:53:58 | C66: AMOL | D66: 7709162306 | E66: MH12HJ2056 | F66: Hero Karizma R | G66: 01 | H66: 0 ₹ | I66: 0 | J66: 6803 | K66: 6803 | L66: 6803 | M66: 5140 | N66: 784 | O66: 879 | P66: Card
A67: F0117-C3687 | B67: 2025-01-17 20:53:42 | C67: Digambar Navrekar | D67: 8668867769 | E67: MH12MT0829 | F67: Honda Shine SP | G67: 01 | H67: 0 ₹ | I67: 0 | J67: 858 | K67: 858 | L67: 858 | M67: 253 | N67: 0 | O67: 605 | P67: UPI | Q67: ME4JC732AG80153370
A68: F0117-C3686 | B68: 2025-01-17 20:54:38 | C68: ATUL NANDGUDE | D68: 9766611011 | E68: MH14EB5971 | F68: Honda Activa 110 | G68: 35135 | H68: 0 ₹ | I68: 0 | J68: 2780 | K68: 2780 | L68: 2780 | M68: 2135 | N68: 120 | O68: 525 | P68: Card
A69: E1130-C3209 | B69: 2024-12-01 18:10:00 | C69: Abhay Raipurkar | D69: 9823126447 | E69: MH12CZ1270 | F69: Honda Activa Old | G69: 64331 | H69: 0 ₹ | I69: 0 | J69: 1793 | K69: 1793 | L69: 1793 | M69: 459 | N69: 730 | O69: 604 | P69: UPI | Q69: ME4JF087J50186236 | R69: JF08E8166329
A70: E1201-C3228 | B70: 2024-12-01 19:05:51 | C70: Sayali Kadam | D70: 7620421309 | E70: MH12KX3002 | F70: Honda Activa | G70: 39086 | H70: 0 ₹ | I70: 0 | J70: 1764 | K70: 1764 | L70: 1764 | M70: 775 | N70: 540 | O70: 449 | P70: UPI | Q70: ME4JF501CE8799577 | R70: JF50E80798509
A71: E1201-C3232 | B71: 2024-12-01 19:52:37 | C71: Yogesh Chavan | D71: 7775061909 | E71: MH12LN9276 | F71: Honda Dream Neo | G71: 39239 | H71: 0 ₹ | I71: 0 | J71: 1713 | K71: 1713 | L71: 1713 | M71: 964 | N71: 0 | O71: 749 | P71: UPI | Q71: ME4JC62AJET006651 | R71: JC62ET1091230
A72: E1201-C3230 | B72: 2024-12-01 17:36:53 | C72: Ashutosh | D72: 7406056477 | E72: MH15JP8584 | F72: TVS Apache RTR 160 | G72: 40552 | H72: 0 ₹ | I72: 0 | J72: 1744 | K72: 1744 | L72: 1744 | M72: 361 | N72: 784 | O72: 599 | P72: UPI | Q72: MD634KE4XGF60465 | R72: OE4FG2008309
A73: E1201-C3233 | B73: 2024-12-01 20:10:34 | C73: Swapnil Akolkar | D73: 7770066606 | E73: MH16BP1559 | F73: Yamaha FZ V3 | G73: 66946 | H73: 0 ₹ | I73: 0 | J73: 3013 | K73: 3013 | L73: 3013 | M73: 1630 | N73: 784 | O73: 599 | P73: UPI | Q73: ME1RG072AF0143688 | R73: G38E0230139
A74: E1201-C3227 | B74: 2024-12-01 20:49:40 | C74: Tushar Gade | D74: 9764004230 | E74: MH14DQ3464 | F74: Honda Activa 110 | G74: 31560 | H74: 0 ₹ | I74: 0 | J74: 3490 | K74: 3490 | L74: 3490 | M74: 2081 | N74: 730 | O74: 679 | P74: UPI | Q74: ME4JC448HC7533351 | R74: JC44E5533375
A75: E1201-C3237 | B75: 2024-12-01 21:15:04 | C75: Gaurav Chaudhari | D75: 8208424628 | E75: MH19DE8406 | F75: Hero Passion XPRO | G75: 35076 | H75: 0 ₹ | I75: 0 | J75: 1729 | K75: 1729 | L75: 1729 | M75: 655 | N75: 0 | O75: 1074 | P75: UPI | Q75: MBLJAR151JGE07143 | R75: JA06ETJGE08787
A76: E1201-C3235 | B76: 2024-12-02 17:02:52 | C76: Abbas | D76: 9028512702 | E76: MH14HN5332 | F76: TVS Jupiter | G76: 17837 | H76: 0 ₹ | I76: 0 | J76: 1400 | K76: 1400 | L76: 1400 | M76: 1350 | N76: 0 | O76: 50 | P76: UPI | Q76: MD626EG48K1B14981 | R76: DG4BK1106673
A77: F0512-C4724 | B77: 2025-05-12 19:44:34 | C77: Yogesh Ingale | D77: 9922412060 | E77: MH14EW7129 | F77: TVS Wego | G77: 5737 | H77: 0 ₹ | I77: 0 | J77: 1926 | K77: 1926 | L77: 1926 | M77: 738 | N77: 739 | O77: 449 | P77: UPI | Q77: MD626AG48E1207593
A78: E1221-C3420 | B78: 2024-12-21 17:03:16 | C78: Astha | D78: 8871618082 | E78: MH40CK6436 | F78: TVS Jupiter | G78: 10679 | H78: 0 ₹ | I78: 0 | J78: 1259 | K78: 1259 | L78: 1259 | M78: 80 | N78: 730 | O78: 449 | P78: Card | Q78: MD62EG57N1C00103 | R78: GG5BN1611977
A79: E1221-C3419 | B79: 2024-12-21 16:48:56 | C79: Ashok Yadav | D79: 9970886964 | E79: MH14EW8848 | F79: Honda Activa | G79: 65155 | H79: 0 ₹ | I79: 0 | J79: 4077 | K79: 4077 | L79: 4077 | M79: 2448 | N79: 730 | O79: 899 | P79: UPI
A80: E1221-C3425 | B80: 2024-12-21 18:57:56 | C80: Prathamesh Nikam | D80: 9766589338 | E80: MH12NH1362 | F80: TVS Jupiter | G80: 32921 | H80: 0 ₹ | I80: 0 | J80: 1959 | K80: 1959 | L80: 1959 | M80: 780 | N80: 730 | O80: 449 | P80: UPI
A81: F0118-C3692 | B81: 2025-01-18 12:04:17 | C81: Pandit Patekari | D81: 9850380576 | E81: MH12FJ2072 | F81: Hero Passion Plus | G81: 47945 | H81: 0 ₹ | I81: 0 | J81: 1362 | K81: 1362 | L81: 1362 | M81: 223 | N81: 190 | O81: 949 | P81: Card
A82: E1201-C3236 | B82: 2024-12-02 17:02:31 | C82: Bhushan Patil | D82: 9822889511 | E82: MH14BS1571 | F82: Honda Unicorn | G82: 51035 | H82: 0 ₹ | I82: 0 | J82: 2014 | K82: 2014 | L82: 2014 | M82: 781 | N82: 784 | O82: 449 | P82: UPI | Q82: ME4KC093M88030825 | R82: K6091031920
A83: E1221-C3428 | B83: 2024-12-22 20:06:57 | C83: SHUBHAM KOTHARI | D83: 8511601644 | E83: MH31DL9819 | F83: Honda Activa 110 | G83: 20000 | H83: 09 ₹ | I83: 0 | J83: 1900 | K83: 1909 | L83: 1900 | M83: 575 | N83: 730 | O83: 604 | P83: UPI
A84: E1221-C3429 | B84: 2024-12-21 19:29:40 | C84: Sairaj | D84: 9172992292 | E84: MH26CD0564 | F84: Yamaha FZ V3 | G84: 25475 | H84: 0 ₹ | I84: 0 | J84: 3303 | K84: 3303 | L84: 3303 | M84: 1470 | N84: 784 | O84: 1049 | P84: Card | Q84: ME1RG6689N0019141 | R84: G3N3E0234542
A85: E1220-C3412 | B85: 2024-12-21 19:32:40 | C85: Abhishek Agrawal | D85: 9920227457 | E85: MH14HN5266 | F85: Suzuki Access | G85: 15841 | H85: 0 ₹ | I85: 0 | J85: 3275 | K85: 3275 | L85: 3275 | M85: 2096 | N85: 730 | O85: 449 | P85: UPI | Q85: MB8DP11AAK8852381
A86: E1221-C3421 | B86: 2024-12-21 19:31:20 | C86: Saurabh Gandhi | D86: 9860645457 | E86: MH25X6443 | F86: Hero Passion Pro | G86: 45948 | H86: 0 ₹ | I86: 0 | J86: 1795 | K86: 1795 | L86: 1795 | M86: 528 | N86: 168 | O86: 1099 | P86: UPI | Q86: MBLHA10EWBHLZ8250 | R86: HA10EDBHIL29364
A87: E1220-C3414 | B87: 2024-12-21 19:58:58 | C87: Sujeet Sanap | D87: 9881212187 | E87: MH14FP0537 | F87: Hero Pleasure | G87: 21184 | H87: 0 ₹ | I87: 0 | J87: 4154 | K87: 4154 | L87: 4154 | M87: 2900 | N87: 730 | O87: 524 | P87: Card
A88: F0512-C4718 | B88: 2025-05-12 19:44:57 | C88: Deepanjan | D88: 7045309011 | E88: MH12NT3423 | F88: Bajaj Avenger 150 Street | G88: 16379 | H88: 0 ₹ | I88: 0 | J88: 2057 | K88: 2057 | L88: 2057 | M88: 683 | N88: 775 | O88: 599 | P88: Cash | Q88: MD2A85CY4GCJ02450 | R88: PDYCGJ58802
A89: E1220-C3409 | B89: 2024-12-21 19:59:39 | C89: Abhijit | D89: 7776830728 | E89: MH19CM2983 | F89: Hero Pleasure | G89: 16129 | H89: 0 ₹ | I89: 0 | J89: 2027 | K89: 2027 | L89: 2027 | M89: 773 | N89: 730 | O89: 524 | P89: Card | R89: JF16EEC9H04524
A90: E1202-C3243 | B90: 2024-12-02 19:01:02 | C90: Pratik Dharpale | D90: 9850698885 | E90: MH14FQ7830 | F90: Honda Activa 3G | G90: 22038 | H90: 0 ₹ | I90: 0 | J90: 2742 | K90: 2742 | L90: 2742 | M90: 1313 | N90: 730 | O90: 699 | P90: Cash | Q90: ME4JF505FGG484875 | R90: JF50E3485007
A91: E1221-C3423 | B91: 2024-12-21 20:04:27 | C91: Bhushan | D91: 9834919277 | E91: MH34AK9719 | F91: Hero Xtreme | G91: 2 | H91: 0 ₹ | I91: 0 | J91: 1328 | K91: 1328 | L91: 1328 | M91: 95 | N91: 784 | O91: 449 | P91: UPI | Q91: MBLKC12EHCLM08292 | R91: KC1ZECCGM0836
A92: E1202-C3241 | B92: 2024-12-02 20:31:54 | C92: Sreeraj | D92: 9987181711 | E92: KA04KE2084 | F92: Yamaha Ray Z | G92: 12581 | H92: 0 ₹ | I92: 0 | J92: 1382 | K92: 1382 | L92: 1382 | M92: 80 | N92: 773 | O92: 529 | P92: UPI | Q92: ME1SEG451M0091971 | R92: E32SE0316375
A93: E1202-C3244 | B93: 2024-12-02 20:30:57 | C93: Brajesh Pandey | D93: 8888808112 | E93: MH14DW1997 | F93: TVS Scooty PEP Plus | G93: 34519 | H93: 0 ₹ | I93: 0 | J93: 2801 | K93: 2801 | L93: 2801 | M93: 2426 | N93: 0 | O93: 375 | P93: UPI
A94: E1202-C3240 | B94: 2024-12-02 20:32:49 | C94: SAURABH BHAVSAR | D94: 8983621730 | E94: MH41AE6793 | F94: Hero Hunk | G94: 59960 | H94: 0 ₹ | I94: 0 | J94: 3055 | K94: 3055 | L94: 3055 | M94: 1099 | N94: 762 | O94: 1194 | P94: UPI | Q94: MBLKC13EGEHD00178 | R94: KC13EFEHD00367
A95: E1202-C3239 | B95: 2024-12-02 19:04:07 | C95: Edwin | D95: 9643533551 | E95: DL9SBC9006 | F95: Suzuki Gixxer SF | G95: 1 | H95: 0 ₹ | I95: 0 | J95: 2178 | K95: 2178 | L95: 2178 | M95: 1390 | N95: 64 | O95: 724 | P95: UPI | Q95: MB81NG4BBHF8115665 | R95: BGA4186316
A96: E1202-C3242 | B96: 2024-12-02 21:04:57 | C96: Kaushik | D96: 9552179245 | E96: MH14EW2215 | F96: Honda Activa 110 | G96: 65403 | H96: 180 ₹ | I96: 0 | J96: 8000 | K96: 8180 | L96: 8000 | M96: 6816 | N96: 730 | O96: 634 | P96: UPI | Q96: ME4JF504BF7012078 | R96: JF50E72012042
A97: F0512-C4726 | B97: 2025-05-12 20:02:59 | C97: Prashant | D97: 7350018212 | E97: MH14KT3518 | F97: Honda Activa 6G | G97: 14831 | H97: 0 ₹ | I97: 0 | J97: 2134 | K97: 2134 | L97: 2134 | M97: 621 | N97: 739 | O97: 774 | P97: UPI | Q97: JK15EG4021H9
A98: F0504-C4648 | B98: 2025-05-04 20:18:58 | C98: AADITYA PATIL | D98: 8623855792 | E98: MH12LP136 | F98: Suzuki Lets | G98: 23990 | H98: 0 ₹ | I98: 0 | J98: 1150 | K98: 1150 | L98: 1150 | M98: 1150 | N98: 0 | O98: 0 | P98: UPI
A99: E1221-C3422 | B99: 2024-12-21 20:14:38 | C99: Ketan Yelnoorkar | D99: 9028366926 | E99: MH20CM4633 | F99: Yamaha FZ S | G99: 22224 | H99: 0 ₹ | I99: 0 | J99: 5354 | K99: 5354 | L99: 5354 | M99: 3516 | N99: 784 | O99: 1054 | P99: UPI | Q99: ME121C0FAC2002589
A100: F0512-C4727 | B100: 2025-05-12 20:12:23 | C100: SHRIKANT | D100: 9945928580 | E100: MH27CE0844 | F100: Bajaj Avenger 220 Street | G100: 32870 | H100: 0 ₹ | I100: 0 | J100: 3353 | K100: 3353 | L100: 3353 | M100: 2128 | N100: 710 | O100: 515 | P100: Cash
...
